keyparser/__init__.py
keyparser-0.0.0.dist-info/METADATA
keyparser-0.0.0.dist-info/WHEEL
keyparser-0.0.0.dist-info/licenses/LICENSE
keyparser-0.0.0.dist-info/RECORD
