Metadata-Version: 2.1
Name: keyparser
Version: 0.0.0
Summary: String Parser by Key
Project-URL: Homepage, https://github.com/chorong8883/keyparser
Author-email: Chor <chorong8883@gmail.com>
License-File: LICENSE
Keywords: keyparser
Classifier: License :: OSI Approved :: MIT License
Classifier: Operating System :: MacOS
Classifier: Operating System :: POSIX :: Linux
Classifier: Programming Language :: Python :: 3.10
Requires-Python: >=3.10
